sparkle2d/__init__.py
sparkle2d/animation.py
sparkle2d/app.py
sparkle2d/audio.py
sparkle2d/camera.py
sparkle2d/ecs.py
sparkle2d/events.py
sparkle2d/inputmap.py
sparkle2d/particles.py
sparkle2d/physics.py
sparkle2d/resources.py
sparkle2d/scene.py
sparkle2d/scripting.py
sparkle2d/tilemap.py
sparkle2d/tween.py
sparkle2d/ui.py
sparkle2d/assets/audio/placeholder.txt
sparkle2d/assets/maps/placeholder.txt
sparkle2d/assets/sprites/placeholder.txt
sparkle2d/plugins/__init__.py
sparkle2d/systems/__init__.py
sparkle2d/systems/input.py
sparkle2d/systems/render.py
sparkle2d-0.5.0.dist-info/licenses/LICENSE
sparkle2d-0.5.0.dist-info/METADATA
sparkle2d-0.5.0.dist-info/WHEEL
sparkle2d-0.5.0.dist-info/top_level.txt
sparkle2d-0.5.0.dist-info/RECORD
