Metadata-Version: 2.4
Name: sparkle2d
Version: 0.5.0
Summary: Lua script destekli 2D oyun motoru (Python + pyglet + lupa)
Author: Baba
License: MIT
Project-URL: Homepage, https://github.com/kullanici/sparkle2d
Project-URL: Repository, https://github.com/kullanici/sparkle2d
Requires-Python: >=3.9
License-File: LICENSE
Requires-Dist: pyglet>=2.0
Requires-Dist: pillow>=10.0
Requires-Dist: lupa>=2.0
Requires-Dist: pymunk>=6.6
Requires-Dist: pytmx>=3.33
Requires-Dist: watchdog>=4.0.0
Requires-Dist: numpy>=1.26
Provides-Extra: dev
Requires-Dist: pytest>=8; extra == "dev"
Requires-Dist: twine; extra == "dev"
Requires-Dist: build; extra == "dev"
Dynamic: license-file
